orcamentobr/__init__.py
orcamentobr/despesa_detalhada.py
orcamentobr/quais_dimensoes.py
orcamentobr/siop_utils.py
orcamentobr/certs/fullchainsiop.pem
orcamentobr-1.0.1.dist-info/licenses/LICENSE
orcamentobr-1.0.1.dist-info/METADATA
orcamentobr-1.0.1.dist-info/WHEEL
orcamentobr-1.0.1.dist-info/top_level.txt
orcamentobr-1.0.1.dist-info/RECORD
