Metadata-Version: 2.4
Name: orcamentobr
Version: 1.0.1
Summary: Download Official Data on Brazil's Federal Budget
Author-email: Daniel Gersten Reiss <daniel.reiss@planejamento.gov.br>, Gabriel Soares Vera <gabriel-soares.vera@planejamento.gov.br>
License: GPL-3.0-or-later
Project-URL: Technical_information, https://www1.siop.planejamento.gov.br/mto/
Classifier: Programming Language :: Python :: 3
Classifier: License :: OSI Approved :: GNU General Public License v3 (GPLv3)
Classifier: Operating System :: OS Independent
Requires-Python: >=3.7
License-File: LICENSE
Requires-Dist: pandas>=2.1
Requires-Dist: requests>=2.30
Dynamic: license-file
